<AstNode xmlns:i="http://www.w3.org/2001/XMLSchema-instance" xmlns="http://schemas.datacontract.org/2004/07/NPEG"><Children><AstNode><Children><AstNode><Children><AstNode><Children><AstNode><Children /><Token><End>27</End><Name>Symbol</Name><Start>22</Start></Token></AstNode></Children><Token><End>27</End><Name>FullSymbol</Name><Start>22</Start></Token></AstNode></Children><Token><End>27</End><Name>NamespaceImport</Name><Start>18</Start></Token></AstNode><AstNode><Children /><Token><End>28</End><Name>EndOfSentence</Name><Start>28</Start></Token></AstNode></Children><Token><End>28</End><Name>Sentence</Name><Start>18</Start></Token></AstNode></Children><Token><End>28</End><Name>Root</Name><Start>0</Start></Token></AstNode>